CHANGES.rst
LICENSE
MANIFEST.in
README.rst
requirements-dev.txt
requirements.txt
setup.cfg
setup.py
mc2/__init__.py
mc2/admin.py
mc2/celery_app.py
mc2/context_processors.py
mc2/forms.py
mc2/models.py
mc2/permissions.py
mc2/settings.py
mc2/socialauth_pipelines.py
mc2/urls.py
mc2/views.py
mc2/wsgi.py
mc2/controllers/__init__.py
mc2/controllers/models.py
mc2/controllers/urls.py
mc2/controllers/base/__init__.py
mc2/controllers/base/admin.py
mc2/controllers/base/builders.py
mc2/controllers/base/exceptions.py
mc2/controllers/base/forms.py
mc2/controllers/base/models.py
mc2/controllers/base/namers.py
mc2/controllers/base/states.py
mc2/controllers/base/tasks.py
mc2/controllers/base/urls.py
mc2/controllers/base/views.py
mc2/controllers/base/workflows.py
mc2/controllers/base/fixtures/test_organizations.json
mc2/controllers/base/fixtures/test_social_auth.json
mc2/controllers/base/fixtures/test_users.json
mc2/controllers/base/managers/__init__.py
mc2/controllers/base/managers/infrastructure.py
mc2/controllers/base/managers/rabbitmq.py
mc2/controllers/base/migrations/0001_initial.py
mc2/controllers/base/migrations/0002_envvariable.py
mc2/controllers/base/migrations/0003_set_default_for_marathon_cmd.py
mc2/controllers/base/migrations/0004_marathonlabel.py
mc2/controllers/base/migrations/0005_field_defaults.py
mc2/controllers/base/migrations/0006_controller_webhook_token.py
mc2/controllers/base/migrations/0007_auto_20160416_1253.py
mc2/controllers/base/migrations/0008_auto_20160907_1857.py
mc2/controllers/base/migrations/0009_additionallink.py
mc2/controllers/base/migrations/0010_add_rabbitmq_fields.py
mc2/controllers/base/migrations/0011_add_on_delete_to_controller_foreignkey.py
mc2/controllers/base/migrations/__init__.py
mc2/controllers/base/templates/app_logs.html
mc2/controllers/base/templates/controller_edit.html
mc2/controllers/base/templates/base/inclusion_tags/controller_object.html
mc2/controllers/base/templatetags/__init__.py
mission_control2.egg-info/PKG-INFO
mission_control2.egg-info/SOURCES.txt
mission_control2.egg-info/dependency_links.txt
mission_control2.egg-info/not-zip-safe
mission_control2.egg-info/requires.txt
mission_control2.egg-info/top_level.txt