Metadata-Version: 1.1
Name: mission-control2
Version: 3.12.0
Summary: Mission Control - allows for easy launching of apps on Marathon
Home-page: http://github.com/praekelt/mc2
Author: Praekelt Foundation
Author-email: dev@praekelt.com
License: BSD
Platform: UNKNOWN
Classifier: Programming Language :: Python
Classifier: Framework :: Django
Classifier: Topic :: Internet :: WWW/HTTP
Classifier: Topic :: Internet :: WWW/HTTP :: WSGI :: Application
